{
  "task_id": "env/make_win-distr_obj_rule",
  "episode": 2,
  "solved": true,
  "progression": 1.0,
  "steps": 26,
  "method": "bfs",
  "actions": [
    "up",
    "right",
    "right",
    "down",
    "right",
    "right",
    "down",
    "down",
    "down",
    "down",
    "left",
    "up",
    "up",
    "up",
    "right",
    "up",
    "left",
    "down",
    "left",
    "up",
    "right",
    "right",
    "down",
    "down",
    "down",
    "down"
  ],
  "bfs_nodes": 3336,
  "elapsed_s": 24.41
}