{
 "ar25": {
  "game": "ar25",
  "n_levels": 8,
  "protocol": "source-simulated (reconstruct+certify, no source)",
  "wall_s": 825.5,
  "certificate": {
   "pass": true,
   "acc": 1.0,
   "acc_lower": 0.9941660443994438,
   "n": 512,
   "exact": 512,
   "eps": 0.01,
   "delta": 0.05,
   "coverage": 0.1111111111111111,
   "coverage_target": 0.0,
   "levelup_match": 0,
   "levelup_total": 0,
   "errored": false
  },
  "champion_acc": 1.0,
  "ab_agreement": 0.970703125,
  "ab_vs_real_gap": 0.0,
  "rounds": 2,
  "real_steps": 976,
  "history": [
   {
    "round": 0,
    "champion": 0,
    "champion_acc": 0.84765625,
    "n_cex": 13,
    "cert_pass": false,
    "coverage": 0.1111111111111111,
    "real_steps": 488
   },
   {
    "round": 1,
    "champion": 0,
    "champion_acc": 1.0,
    "n_cex": 0,
    "cert_pass": true,
    "coverage": 0.1111111111111111,
    "real_steps": 976
   }
  ],
  "engine_src": "class Engine:\n    A_CELLS = [(0,0),(0,1),(0,2),(1,2),(2,2)]\n    B_CELLS = [(0,0),(0,1),(0,2),(1,0),(2,0)]\n    def __init__(self):\n        self.state = {'levels': 0, 'count': 0, 'A': [15,18], 'B': [15,36], 'hist': []}\n        self._build_base()\n    def _build_base(self):\n        b = np.full((64,64), 9, dtype=int)\n        b[0:63, 30:33] = 10\n        b[45:48, 51:60] = 11\n        b[48:54, 51:54] = 11\n        b[:, 63] = 11\n        b[63, 0:63] = 5\n        self.base = b\n    def reset(self):\n        self.state['A'] = [15,18]\n        self.state['B'] = [15,36]\n        self.state['hist'] = []\n        self.state['count'] = 0\n        self.state['levels'] = 0\n        self._build_base()\n        return self._render()\n    def _clamp(self, p):\n        p[0] = max(0, min(55, p[0]))\n        p[1] = max(0, min(55, p[1]))\n    def step(self, action):\n        kind = action[0]\n        A = self.state['A']; B = self.state['B']\n        if kind in (1,2,3,4):\n            self.state['hist'].append((list(A), list(B)))\n            if kind == 1:\n                A[0]-=3; B[0]-=3\n            elif kind == 2:\n                A[0]+=3; B[0]+=3\n            elif kind == 3:\n                A[1]-=3; B[1]+=3\n            elif kind == 4:\n                A[1]+=3; B[1]-=3\n            self._clamp(A); self._clamp(B)\n            self.state['count'] += 1\n        elif kind == 5:\n            self.state['count'] += 1\n        elif kind == 7:\n            if self.state['hist']:\n                pa, pb = self.state['hist'].pop()\n                self.state['A'] = pa; self.state['B'] = pb\n        return self._render()\n    def _render(self):\n        g = self.base.copy()\n        k = min(self.state['count'], 63)\n        if k > 0:\n            g[0:k, 63] = 5\n        ref = g.copy()\n        br, bc = self.state['B']\n        for (cr, cc) in self.B_CELLS:\n            r0 = br+3*cr; c0 = bc+3*cc\n            g[r0:r0+3, c0:c0+3] = 4\n        ar, ac = self.state['A']\n        for (cr, cc) in self.A_CELLS:\n            r0 = ar+3*cr; c0 = ac+3*cc\n            g[r0:r0+3, c0:c0+3] = 5\n            hr = r0+1; hc = c0+1\n            v = ref[hr, hc]\n            g[hr, hc] = v if v != 9 else 0\n        return g\n    def is_win(self, prev_frame):\n        return self.state.get('levels', 0) > 0",
  "error": null
 }
}