{
  "games": {
    "ar25": {
      "card_renders": true,
      "depth_real": 8,
      "depth_through_world": 8,
      "game": "ar25",
      "indexed_fallback": false,
      "misses": 0,
      "n_actions": 253,
      "n_states": 254,
      "n_transitions": 253,
      "pass": true,
      "spec_valid": true
    },
    "bp35": {
      "card_renders": true,
      "depth_real": 7,
      "depth_through_world": 7,
      "game": "bp35",
      "indexed_fallback": false,
      "misses": 0,
      "n_actions": 225,
      "n_states": 226,
      "n_transitions": 225,
      "pass": true,
      "spec_valid": true
    },
    "cd82": {
      "card_renders": true,
      "depth_real": 6,
      "depth_through_world": 6,
      "game": "cd82",
      "indexed_fallback": false,
      "misses": 0,
      "n_actions": 91,
      "n_states": 91,
      "n_transitions": 91,
      "pass": true,
      "spec_valid": true
    },
    "cn04": {
      "card_renders": true,
      "depth_real": 6,
      "depth_through_world": 6,
      "game": "cn04",
      "indexed_fallback": false,
      "misses": 0,
      "n_actions": 291,
      "n_states": 292,
      "n_transitions": 291,
      "pass": true,
      "spec_valid": true
    },
    "dc22": {
      "card_renders": true,
      "depth_real": 6,
      "depth_through_world": 6,
      "game": "dc22",
      "indexed_fallback": true,
      "misses": 0,
      "n_actions": 426,
      "n_states": 427,
      "n_transitions": 426,
      "pass": true,
      "spec_valid": true
    },
    "ft09": {
      "card_renders": true,
      "depth_real": 6,
      "depth_through_world": 6,
      "game": "ft09",
      "indexed_fallback": false,
      "misses": 0,
      "n_actions": 80,
      "n_states": 81,
      "n_transitions": 80,
      "pass": true,
      "spec_valid": true
    },
    "g50t": {
      "card_renders": true,
      "depth_real": 7,
      "depth_through_world": 7,
      "game": "g50t",
      "indexed_fallback": false,
      "misses": 0,
      "n_actions": 289,
      "n_states": 290,
      "n_transitions": 289,
      "pass": true,
      "spec_valid": true
    },
    "ka59": {
      "card_renders": true,
      "depth_real": 7,
      "depth_through_world": 7,
      "game": "ka59",
      "indexed_fallback": false,
      "misses": 0,
      "n_actions": 256,
      "n_states": 257,
      "n_transitions": 256,
      "pass": true,
      "spec_valid": true
    },
    "lf52": {
      "card_renders": true,
      "depth_real": 6,
      "depth_through_world": 6,
      "game": "lf52",
      "indexed_fallback": false,
      "misses": 0,
      "n_actions": 318,
      "n_states": 319,
      "n_transitions": 318,
      "pass": true,
      "spec_valid": true
    },
    "lp85": {
      "card_renders": true,
      "depth_real": 8,
      "depth_through_world": 8,
      "game": "lp85",
      "indexed_fallback": false,
      "misses": 0,
      "n_actions": 79,
      "n_states": 80,
      "n_transitions": 79,
      "pass": true,
      "spec_valid": true
    },
    "ls20": {
      "card_renders": true,
      "depth_real": 7,
      "depth_through_world": 7,
      "game": "ls20",
      "indexed_fallback": false,
      "misses": 0,
      "n_actions": 309,
      "n_states": 310,
      "n_transitions": 309,
      "pass": true,
      "spec_valid": true
    },
    "m0r0": {
      "card_renders": true,
      "depth_real": 6,
      "depth_through_world": 6,
      "game": "m0r0",
      "indexed_fallback": false,
      "misses": 0,
      "n_actions": 220,
      "n_states": 221,
      "n_transitions": 220,
      "pass": true,
      "spec_valid": true
    },
    "r11l": {
      "card_renders": true,
      "depth_real": 6,
      "depth_through_world": 6,
      "game": "r11l",
      "indexed_fallback": false,
      "misses": 0,
      "n_actions": 84,
      "n_states": 85,
      "n_transitions": 84,
      "pass": true,
      "spec_valid": true
    },
    "re86": {
      "card_renders": true,
      "depth_real": 8,
      "depth_through_world": 8,
      "game": "re86",
      "indexed_fallback": false,
      "misses": 0,
      "n_actions": 602,
      "n_states": 603,
      "n_transitions": 602,
      "pass": true,
      "spec_valid": true
    },
    "s5i5": {
      "card_renders": true,
      "depth_real": 8,
      "depth_through_world": 8,
      "game": "s5i5",
      "indexed_fallback": false,
      "misses": 0,
      "n_actions": 282,
      "n_states": 283,
      "n_transitions": 282,
      "pass": true,
      "spec_valid": true
    },
    "sb26": {
      "card_renders": true,
      "depth_real": 8,
      "depth_through_world": 8,
      "game": "sb26",
      "indexed_fallback": false,
      "misses": 0,
      "n_actions": 131,
      "n_states": 125,
      "n_transitions": 131,
      "pass": true,
      "spec_valid": true
    },
    "sc25": {
      "card_renders": true,
      "depth_real": 6,
      "depth_through_world": 6,
      "game": "sc25",
      "indexed_fallback": false,
      "misses": 0,
      "n_actions": 122,
      "n_states": 122,
      "n_transitions": 122,
      "pass": true,
      "spec_valid": true
    },
    "sk48": {
      "card_renders": true,
      "depth_real": 8,
      "depth_through_world": 8,
      "game": "sk48",
      "indexed_fallback": false,
      "misses": 0,
      "n_actions": 248,
      "n_states": 249,
      "n_transitions": 248,
      "pass": true,
      "spec_valid": true
    },
    "sp80": {
      "card_renders": true,
      "depth_real": 6,
      "depth_through_world": 6,
      "game": "sp80",
      "indexed_fallback": false,
      "misses": 0,
      "n_actions": 134,
      "n_states": 135,
      "n_transitions": 134,
      "pass": true,
      "spec_valid": true
    },
    "su15": {
      "card_renders": true,
      "depth_real": 9,
      "depth_through_world": 9,
      "game": "su15",
      "indexed_fallback": false,
      "misses": 0,
      "n_actions": 105,
      "n_states": 106,
      "n_transitions": 105,
      "pass": true,
      "spec_valid": true
    },
    "tn36": {
      "card_renders": true,
      "depth_real": 7,
      "depth_through_world": 7,
      "game": "tn36",
      "indexed_fallback": false,
      "misses": 0,
      "n_actions": 104,
      "n_states": 105,
      "n_transitions": 104,
      "pass": true,
      "spec_valid": true
    },
    "tr87": {
      "card_renders": true,
      "depth_real": 6,
      "depth_through_world": 6,
      "game": "tr87",
      "indexed_fallback": false,
      "misses": 0,
      "n_actions": 127,
      "n_states": 128,
      "n_transitions": 127,
      "pass": true,
      "spec_valid": true
    },
    "tu93": {
      "card_renders": true,
      "depth_real": 9,
      "depth_through_world": 9,
      "game": "tu93",
      "indexed_fallback": false,
      "misses": 0,
      "n_actions": 185,
      "n_states": 186,
      "n_transitions": 185,
      "pass": true,
      "spec_valid": true
    },
    "vc33": {
      "card_renders": true,
      "depth_real": 7,
      "depth_through_world": 7,
      "game": "vc33",
      "indexed_fallback": false,
      "misses": 0,
      "n_actions": 270,
      "n_states": 271,
      "n_transitions": 270,
      "pass": true,
      "spec_valid": true
    },
    "wa30": {
      "card_renders": true,
      "depth_real": 9,
      "depth_through_world": 9,
      "game": "wa30",
      "indexed_fallback": false,
      "misses": 0,
      "n_actions": 657,
      "n_states": 654,
      "n_transitions": 657,
      "pass": true,
      "spec_valid": true
    }
  },
  "n_pass": 25,
  "n_total": 25,
  "note": "each ARC-AGI-3 solve re-verified through an OpenWorld World (FunctionTransition over the discovered masked-frame state graph; reward = levels_completed); solution replayed via world.step and asserted to reproduce the verified depth."
}